{
    "attributeEntries": {
        "NO_PASSIVE": "No passive effect",
        "NO_SPECIAL": "No armor special",

        "CAN_BE_DESTROYED": "Destructible",
        "CANNOT_BE_DESTROYED": "Indestructible",

        "HAS_SET": "Is part of a set",
        "NO_SET": "Not part of a set",

        "CAN_BE_RECOLORED": "Can change color type",
        "CANNOT_RECOLOR": "Cannot change color type",
        
        "CAN_BE_REMOVED": "Removable",
        "CANNOT_BE_REMOVED": "Cannot be removed",

        "DAMAGES_ON_REMOVAL": "Damages user if removed",
        
        "CAN_BE_ONYXED": "Can be Onyx-modded",
        "CANNOT_BE_ONYXED": "Can't be Onyx-modded",
        "ALREADY_ONYXED": "Already Onyx-modded",
        
        "CAN_BE_REPAIRED": "Repairable",
        "CANNOT_BE_REPAIRED": "Cannot be conventionally repaired",
        "NO_REPAIR_NEEDED": "Does not need repairs",

        "HAS_AUTO_REPAIR": "Repairs itself overtime",
        "NO_AUTO_REPAIR": "Does not repair itself"
    }
}
